gdshechka.py
gdshechka-2.4.dist-info/METADATA
gdshechka-2.4.dist-info/WHEEL
gdshechka-2.4.dist-info/RECORD
