Metadata-Version: 2.1
Name: gdshechka
Version: 2.4
Summary: 
Author: N1C1
Requires-Python: >=3.12,<4.0
Classifier: Programming Language :: Python :: 3
Classifier: Programming Language :: Python :: 3.12
Classifier: Programming Language :: Python :: 3.13
Requires-Dist: bs4 (>=0,<1)
Requires-Dist: requests (>=0,<1)
